Metadata-Version: 2.1
Name: django-firebase-filefield
Version: 2.0.0
Summary: An Unofficial Django and Firebase Library
Home-page: UNKNOWN
Author: Issei Momonge
Author-email: mggyggf@gmail.com
License: MIT License
Keywords: django,firebase,filefield,django firebase,django firebase filefield,firebase filefield
Platform: UNKNOWN
License-File: LICENCE
